plumber.py
picles.plumber-0.11.dist-info/DESCRIPTION.rst
picles.plumber-0.11.dist-info/METADATA
picles.plumber-0.11.dist-info/RECORD
picles.plumber-0.11.dist-info/WHEEL
picles.plumber-0.11.dist-info/metadata.json
picles.plumber-0.11.dist-info/top_level.txt
