Metadata-Version: 2.0
Name: picles.plumber
Version: 0.11
Summary: Simple data transformation pipeline.
Home-page: https://github.com/picleslivre/plumber/
Author: Gustavo Fonseca & contributors
Author-email: gustavo@gfonseca.net
License: BSD
Platform: UNKNOWN
Classifier: Development Status :: 5 - Production/Stable
Classifier: Intended Audience :: Developers
Classifier: Programming Language :: Python
Classifier: Topic :: Software Development :: Libraries :: Python Modules
Classifier: Programming Language :: Python :: 2.7
Classifier: Programming Language :: Python :: 3.3
Classifier: Programming Language :: Python :: 3.4
